hdl/project_1/project_1.srcs/sources_1/new/Block.v
`timescale 1ns / 1ps

module clock24(clk, time_in, time_out, reset,Alarm,ring);
  input clk, reset; 
  input [16:0] time_in,Alarm; 
  output [16:0] time_out; 
  output ring;
  wire [5:0] sec_in, min_in;
  wire [4:0] hour_in;
  reg [5:0] sec_reg, min_reg;
  reg [4:0] hour_reg;
  reg ring; 
  assign {hour_in, min_in, sec_in} = time_in;
  always@(posedge clk or posedge reset)
    begin
      if(reset)
        begin
          sec_reg <= sec_in;
        end
      else
        begin
          sec_reg <= (sec_reg == 6'd59) ? 6'd0 : (sec_reg + 6'd1);
        end
    end

  always@(posedge clk or posedge reset)
    begin
      if(reset)
        begin
          min_reg <= min_in;
        end
      else
        begin
          if(sec_reg == 6'd59)
            begin
              min_reg <= (min_reg == 6'd59) ? 6'd0 : (min_reg + 6'd1);
            end
        end
    end

  //handle hours
  always@(posedge clk or posedge reset)
    begin
      if(reset)
        begin
          hour_reg <= hour_in;
        end
      else
        begin
          if((sec_reg == 6'd59)&(min_reg == 6'd59))
            begin
              hour_reg <= (hour_reg == 5'd23) ? 5'd0 : (hour_reg + 5'd1);
            end
        end
    end

 assign time_out = {hour_reg, min_reg, sec_reg};

//Alarm    
    always@(*)
     begin
        if(Alarm==time_out)
        begin
        ring =1'd1;
        #50 ring  = 1'd0;
      end
    end

endmodule

hdl/project_1/project_1.srcs/sim_1/new/stimulus.v
`timescale 1ns / 1ps

module stimulus();
    reg clk, reset;
    reg [16:0] time_in,Alarm;
    wire [16:0] time_out; // 5+6+6 = 17
    wire [5:0] sec, min; // 59 = 111011
    wire [4:0] hour; // 24 = 11000
    wire ring;

    
    clock24 c(clk, time_in, time_out, reset,Alarm,ring);
    assign {hour, min, sec} = time_out;

    always #5  clk = ~clk;

    initial
        begin
            clk = 0;
            reset = 0;
            time_in = 17'b10111_110000_000000; //23:48:00
            Alarm = 17'b10111_110001_000000;
            #12
            reset = 1;
            #10
            reset = 0;
            #10000000
            $finish;
        end

    initial //to get simulation outputs
      begin  
        $dumpfile("output_waveform.vcd"); 
        $dumpvars(1, hour);
        $dumpvars(2, min);
        $dumpvars(3, sec);
        $dumpvars(4, ring); 
      end

endmodule

hdl/project_1/project_1.sim/sim_1/behav/xsim/output_waveform.vcd
$date
   Thu Apr 13 08:56:41 2023
$end
$version
  2017.4
$end
$timescale
  1ps
$end
$scope module stimulus $end
$var wire 6 # sec [5:0] $end
$var wire 6 " min [5:0] $end
$var wire 5 ! hour [4:0] $end
$var wire 1 $ ring $end
$upscope $end
$enddefinitions $end
#0
$dumpvars
bx !
bx "
bx #
x$
$end
#12000
b10111 !
b110000 "
b0 #
#25000
b10111 !
b110000 "
b1 #
#35000
b10111 !
b110000 "
b10 #
#45000
b10111 !
b110000 "
b11 #
#55000
b10111 !
b110000 "
b100 #
#65000
b10111 !
b110000 "
b101 #
#75000
b10111 !
b110000 "
b110 #
#85000
b10111 !
b110000 "
b111 #
#95000
b10111 !
b110000 "
b1000 #
#105000
b10111 !
b110000 "
b1001 #
#115000
b10111 !
b110000 "
b1010 #
#125000
b10111 !
b110000 "
b1011 #
#135000
b10111 !
b110000 "
b1100 #
#145000
b10111 !
b110000 "
b1101 #
#155000
b10111 !
b110000 "
b1110 #
#165000
b10111 !
b110000 "
b1111 #
#175000
b10111 !
b110000 "
b10000 #
#185000
b10111 !
b110000 "
b10001 #
#195000
b10111 !
b110000 "
b10010 #
#205000
b10111 !
b110000 "
b10011 #
#215000
b10111 !
b110000 "
b10100 #
#225000
b10111 !
b110000 "
b10101 #
#235000
b10111 !
b110000 "
b10110 #
#245000
b10111 !
b110000 "
b10111 #
#255000
b10111 !
b110000 "
b11000 #
#265000
b10111 !
b110000 "
b11001 #
#275000
b10111 !
b110000 "
b11010 #
#285000
b10111 !
b110000 "
b11011 #
#295000
b10111 !
b110000 "
b11100 #
#305000
b10111 !
b110000 "
b11101 #
#315000
b10111 !
b110000 "
b11110 #
#325000
b10111 !
b110000 "
b11111 #
#335000
b10111 !
b110000 "
b100000 #
#345000
b10111 !
b110000 "
b100001 #
#355000
b10111 !
b110000 "
b100010 #
#365000
b10111 !
b110000 "
b100011 #
#375000
b10111 !
b110000 "
b100100 #
#385000
b10111 !
b110000 "
b100101 #
#395000
b10111 !
b110000 "
b100110 #
#405000
b10111 !
b110000 "
b100111 #
#415000
b10111 !
b110000 "
b101000 #
#425000
b10111 !
b110000 "
b101001 #
#435000
b10111 !
b110000 "
b101010 #
#445000
b10111 !
b110000 "
b101011 #
#455000
b10111 !
b110000 "
b101100 #
#465000
b10111 !
b110000 "
b101101 #
#475000
b10111 !
b110000 "
b101110 #
#485000
b10111 !
b110000 "
b101111 #
#495000
b10111 !
b110000 "
b110000 #
#505000
b10111 !
b110000 "
b110001 #
#515000
b10111 !
b110000 "
b110010 #
#525000
b10111 !
b110000 "
b110011 #
#535000
b10111 !
b110000 "
b110100 #
#545000
b10111 !
b110000 "
b110101 #
#555000
b10111 !
b110000 "
b110110 #
#565000
b10111 !
b110000 "
b110111 #
#575000
b10111 !
b110000 "
b111000 #
#585000
b10111 !
b110000 "
b111001 #
#595000
b10111 !
b110000 "
b111010 #
#605000
b10111 !
b110000 "
b111011 #
#615000
b10111 !
b110001 "
b0 #
1$
#625000
b10111 !
b110001 "
b1 #
#635000
b10111 !
b110001 "
b10 #
#645000
b10111 !
b110001 "
b11 #
#655000
b10111 !
b110001 "
b100 #
#665000
b10111 !
b110001 "
b101 #
0$
#675000
b10111 !
b110001 "
b110 #
#685000
b10111 !
b110001 "
b111 #
#695000
b10111 !
b110001 "
b1000 #
#705000
b10111 !
b110001 "
b1001 #
#715000
b10111 !
b110001 "
b1010 #
#725000
b10111 !
b110001 "
b1011 #
#735000
b10111 !
b110001 "
b1100 #
#745000
b10111 !
b110001 "
b1101 #
#755000
b10111 !
b110001 "
b1110 #
#765000
b10111 !
b110001 "
b1111 #
#775000
b10111 !
b110001 "
b10000 #
#785000
b10111 !
b110001 "
b10001 #
#795000
b10111 !
b110001 "
b10010 #
#805000
b10111 !
b110001 "
b10011 #
#815000
b10111 !
b110001 "
b10100 #
#825000
b10111 !
b110001 "
b10101 #
#835000
b10111 !
b110001 "
b10110 #
#845000
b10111 !
b110001 "
b10111 #
#855000
b10111 !
b110001 "
b11000 #
#865000
b10111 !
b110001 "
b11001 #
#875000
b10111 !
b110001 "
b11010 #
#885000
b10111 !
b110001 "
b11011 #
#895000
b10111 !
b110001 "
b11100 #
#905000
b10111 !
b110001 "
b11101 #
#915000
b10111 !
b110001 "
b11110 #
#925000
b10111 !
b110001 "
b11111 #
#935000
b10111 !
b110001 "
b100000 #
#945000
b10111 !
b110001 "
b100001 #
#955000
b10111 !
b110001 "
b100010 #
#965000
b10111 !
b110001 "
b100011 #
#975000
b10111 !
b110001 "
b100100 #
#985000
b10111 !
b110001 "
b100101 #
